markdown_cjk_spacing/__init__.py
markdown_cjk_spacing/cjk_spacing.py
markdown_cjk_spacing-0.2.2.dist-info/LICENSE
markdown_cjk_spacing-0.2.2.dist-info/METADATA
markdown_cjk_spacing-0.2.2.dist-info/WHEEL
markdown_cjk_spacing-0.2.2.dist-info/entry_points.txt
markdown_cjk_spacing-0.2.2.dist-info/top_level.txt
markdown_cjk_spacing-0.2.2.dist-info/RECORD
