Metadata-Version: 2.1
Name: markdown-cjk-spacing
Version: 0.2.2
Summary: Python markdown extension for insert a space between Chinese / Japanese / Korean and English words
Home-page: https://github.com/EloiseSeverin/markdown_cjk_spacing/
Author: Eloise Severin
Author-email: Eloise.severin @ gmail.com
License: MIT
Keywords: Markdown,extension,plugin,CJK
Platform: UNKNOWN
Classifier: Intended Audience :: Developers
Classifier: Topic :: Software Development :: Build Tools
Classifier: License :: OSI Approved :: MIT License
Classifier: Programming Language :: Python :: 3
Requires-Dist: Markdown (>=3.0.0)
